justtryout/__init__.py
justtryout/main.py
justtryout-0.1.0.dist-info/METADATA
justtryout-0.1.0.dist-info/WHEEL
justtryout-0.1.0.dist-info/entry_points.txt
justtryout-0.1.0.dist-info/RECORD
