Metadata-Version: 2.4
Name: justtryout
Version: 0.1.0
Summary: Add your description here
Requires-Python: >=3.11
Requires-Dist: typer>=0.16.1
